setup.py
ImportConfig.egg-info/PKG-INFO
ImportConfig.egg-info/SOURCES.txt
ImportConfig.egg-info/dependency_links.txt
ImportConfig.egg-info/requires.txt
ImportConfig.egg-info/top_level.txt
importconfig/__init__.py
importconfig/exceptions.py
importconfig/importconfig.py
importconfig/jsonconfig.py
importconfig/yamlconfig.py