Metadata-Version: 1.1
Name: ImportConfig
Version: 0.0.2
Summary: JSON and YAML parsing with imports.
Home-page: https://github.com/Dinoshauer/ImportConfig
Author: Kasper M. Jacobsen
Author-email: k@mackwerk.dk
License: MIT
Platform: UNKNOWN
Classifier: License :: OSI Approved :: MIT License
